[{"foods":[{"category_id":9619183,"discount_activity":"","discount_rate":0.88,"food_id":523576695,"food_rate":"7人好评","icon_name":"特","id":523576695,"image_path":"8f5ee6b77e13ddd28aab93143cfc5a98jpeg","is_new":false,"month_sales":29,"name":"鱼众不同冒菜套餐","original_price":42,"packing_fee":2,"price":37,"restaurant_id":426921,"restaurant_name":"U鼎冒菜（珠市口店）","satisfy_count":7,"satisfy_rate":100,"sku_id":"136502536128","stock":9951}]},{"foods":[{"category_id":515357643,"discount_activity":"","discount_rate":0.5,"food_id":626129194,"food_rate":"50人好评","icon_name":"5","id":626129194,"image_path":"7f3f964abf53be190504c7cbf6d6e80ejpeg","is_new":true,"month_sales":225,"name":"烧茄子+狮子头+关东煮套餐","original_price":25,"packing_fee":1.5,"price":12.5,"restaurant_id":1194075,"restaurant_name":"田老师红烧肉（东城东花市店 ）","satisfy_count":50,"satisfy_rate":96,"sku_id":"241516295155","stock":9988}]},{"foods":[{"category_id":9619183,"discount_activity":"","discount_rate":0.5,"food_id":611269943,"food_rate":"2人好评","icon_name":"折","id":611269943,"image_path":"6fae6e252a6e2dcc6a952910047e1b47jpeg","is_new":false,"month_sales":3,"name":"小U家邂逅冒菜套餐","original_price":43,"packing_fee":2,"price":21.5,"restaurant_id":426921,"restaurant_name":"U鼎冒菜（珠市口店）","satisfy_count":2,"satisfy_rate":100,"sku_id":"226300422080","stock":9993}]},{"foods":[{"category_id":506358215,"discount_activity":"","discount_rate":0.76,"food_id":566231292,"food_rate":"0人好评","icon_name":"特","id":566231292,"image_path":"5c216e9df508e6605aa8ef1eee725d2cpng","is_new":false,"month_sales":7,"name":"双人超值餐","original_price":69,"packing_fee":0,"price":52.5,"restaurant_id":406894,"restaurant_name":"吉野家(北京站店)","satisfy_count":0,"satisfy_rate":0,"sku_id":"180180842969","stock":9957}]},{"foods":[{"category_id":501603074,"discount_activity":"","discount_rate":0.5,"food_id":551664311,"food_rate":"0人好评","icon_name":"折","id":551664311,"image_path":"92dda27f6eada0c7c546532499065ba1jpeg","is_new":false,"month_sales":4,"name":"茶树咖喱鱼排特价套餐","original_price":33.5,"packing_fee":0,"price":16.75,"restaurant_id":278977,"restaurant_name":"一品三笑(东方广场店)","satisfy_count":0,"satisfy_rate":0,"sku_id":"165264254310","stock":1}]},{"foods":[{"category_id":501603074,"discount_activity":"","discount_rate":0.7,"food_id":512687052,"food_rate":"0人好评","icon_name":"折","id":512687052,"image_path":"5a6053aa01c0d276ad42e7707485d1cdjpeg","is_new":false,"month_sales":2,"name":"卤肉饭特价套餐","original_price":29,"packing_fee":0,"price":20.3,"restaurant_id":278977,"restaurant_name":"一品三笑(东方广场店)","satisfy_count":0,"satisfy_rate":0,"sku_id":"125351541094","stock":3}]},{"foods":[{"category_id":504322871,"discount_activity":"","discount_rate":0.5,"food_id":93158191,"food_rate":"1人好评","icon_name":"折","id":93158191,"image_path":"21ea7397a40a584beb8aa41eec77c454jpeg","is_new":false,"month_sales":25,"name":"豉汁蒸凤爪","original_price":25,"packing_fee":1,"price":12.5,"restaurant_id":320366,"restaurant_name":"避风塘（北京崇文门新世界店）","satisfy_count":1,"satisfy_rate":100,"sku_id":"14403390178","stock":9977}]},{"foods":[{"category_id":515354911,"discount_activity":"","discount_rate":0.5,"food_id":634785530,"food_rate":"44人好评","icon_name":"5","id":634785530,"image_path":"cb4fec950540b89331a4289afdbb150djpeg","is_new":true,"month_sales":163,"name":"咖喱鸡+番茄鸡蛋","original_price":20,"packing_fee":1.5,"price":10,"restaurant_id":1194075,"restaurant_name":"田老师红烧肉（东城东花市店 ）","satisfy_count":44,"satisfy_rate":91,"sku_id":"250380383219","stock":9941}]},{"foods":[{"category_id":13218002,"discount_activity":"","discount_rate":0.6,"food_id":568983063,"food_rate":"5人好评","icon_name":"特","id":568983063,"image_path":"29b22ebd7b518aa6c83190658aba5bf2jpeg","is_new":true,"month_sales":17,"name":"劲辣鸭腿煲+可乐套餐","original_price":33,"packing_fee":1,"price":19.8,"restaurant_id":1273384,"restaurant_name":"仔皇煲(磁器口店)","satisfy_count":5,"satisfy_rate":100,"sku_id":"182998656146","stock":9988}]},{"foods":[{"category_id":515321361,"discount_activity":"","discount_rate":0.7,"food_id":625492963,"food_rate":"6人好评","icon_name":"折","id":625492963,"image_path":"ecc2ddd2622bfaeb61d7d3eac0088e08jpeg","is_new":false,"month_sales":38,"name":"香汁排骨满足餐","original_price":36.5,"packing_fee":2,"price":25.55,"restaurant_id":429172,"restaurant_name":"真功夫(北京搜秀店)","satisfy_count":6,"satisfy_rate":100,"sku_id":"240864794481","stock":8988}]},{"foods":[{"category_id":13722720,"discount_activity":"","discount_rate":0.5,"food_id":563235639,"food_rate":"8人好评","icon_name":"折","id":563235639,"image_path":"8df415e279d73dc789176d7c952b3ce8jpeg","is_new":false,"month_sales":31,"name":"A帕帕罗尼比萨[芝心][10 寸]","original_price":90,"packing_fee":0,"price":45,"restaurant_id":308607,"restaurant_name":"必胜客宅急送（磁器口店）","satisfy_count":8,"satisfy_rate":100,"sku_id":"177113295202","stock":99997}]},{"foods":[{"category_id":4556302,"discount_activity":"","discount_rate":0.49,"food_id":524938935,"food_rate":"0人好评","icon_name":"特","id":524938935,"image_path":"e7fe3b5e9dc65a552bc2ed18abb1ce85jpeg","is_new":false,"month_sales":1,"name":"法式黑松露牛肉比萨12英寸（经典手拍法式黑松露酱）","original_price":95,"packing_fee":0,"price":47,"restaurant_id":385177,"restaurant_name":"达美乐比萨（崇文门店）","satisfy_count":0,"satisfy_rate":0,"sku_id":"137897469537","stock":99997}]},{"foods":[{"category_id":15881949,"discount_activity":"","discount_rate":0.74,"food_id":664200022,"food_rate":"4人好评","icon_name":"特","id":664200022,"image_path":"9a44400b3ec6af4496a014145930f0c3jpeg","is_new":false,"month_sales":9,"name":"“双人”餐","original_price":119,"packing_fee":0,"price":88,"restaurant_id":385177,"restaurant_name":"达美乐比萨（崇文门店）","satisfy_count":4,"satisfy_rate":100,"sku_id":"280500822625","stock":99991}]},{"foods":[{"category_id":506358215,"discount_activity":"","discount_rate":0.75,"food_id":566226860,"food_rate":"5人好评","icon_name":"特","id":566226860,"image_path":"e5dfb21939e219b5094d27b31db29d28png","is_new":false,"month_sales":22,"name":"双人优惠餐","original_price":59,"packing_fee":0,"price":44.5,"restaurant_id":406894,"restaurant_name":"吉野家(北京站店)","satisfy_count":5,"satisfy_rate":100,"sku_id":"180176304601","stock":9942}]},{"foods":[{"category_id":13218002,"discount_activity":"","discount_rate":0.5,"food_id":559692552,"food_rate":"0人好评","icon_name":"折","id":559692552,"image_path":"4730041672eaf537d870dea467e9c138jpeg","is_new":true,"month_sales":15,"name":"劲辣鸭腿堡乌梅汁套餐","original_price":52,"packing_fee":2,"price":26,"restaurant_id":1273384,"restaurant_name":"仔皇煲(磁器口店)","satisfy_count":0,"satisfy_rate":0,"sku_id":"173485172882","stock":9985}]},{"foods":[{"category_id":511148561,"discount_activity":"","discount_rate":0.5,"food_id":650190877,"food_rate":"0人好评","icon_name":"折","id":650190877,"image_path":"a949ada59d49b6125a7a0b847d91d18bjpeg","is_new":false,"month_sales":0,"name":"鹅肠（例）","original_price":32,"packing_fee":1,"price":16,"restaurant_id":150088721,"restaurant_name":"小辉哥火锅（北京国瑞店）","satisfy_count":0,"satisfy_rate":0,"sku_id":"266155457810","stock":10000}]},{"foods":[{"category_id":514022912,"discount_activity":"","discount_rate":0.62,"food_id":683259792,"food_rate":"0人好评","icon_name":"特","id":683259792,"image_path":"4aa23abe4d1c9c63423a5ace1ca6449fjpeg","is_new":false,"month_sales":0,"name":"舞茸","original_price":39,"packing_fee":1,"price":24,"restaurant_id":150088721,"restaurant_name":"小辉哥火锅（北京国瑞店）","satisfy_count":0,"satisfy_rate":0,"sku_id":"300018026770","stock":10000}]},{"foods":[{"category_id":515321361,"discount_activity":"","discount_rate":0.7,"food_id":625501443,"food_rate":"11人好评","icon_name":"折","id":625501443,"image_path":"b3789cd8d19401bf423f8ca155af6f7cjpeg","is_new":false,"month_sales":89,"name":"鲜辣排骨满足餐","original_price":36.5,"packing_fee":2,"price":25.55,"restaurant_id":429172,"restaurant_name":"真功夫(北京搜秀店)","satisfy_count":11,"satisfy_rate":100,"sku_id":"240873478001","stock":8990}]},{"foods":[{"category_id":516704180,"discount_activity":"","discount_rate":0.7,"food_id":557593616,"food_rate":"1人好评","icon_name":"折","id":557593616,"image_path":"95bcc3c57aa632e6ecf0163633464eefjpeg","is_new":false,"month_sales":4,"name":"武汉传奇锁骨（微辣）190g/盒","original_price":20,"packing_fee":0,"price":14,"restaurant_id":1517091,"restaurant_name":"久久丫（北京东城桥湾店）","satisfy_count":1,"satisfy_rate":100,"sku_id":"171335863230","stock":9996}]},{"foods":[{"category_id":504326077,"discount_activity":"","discount_rate":0.59,"food_id":145744735,"food_rate":"4人好评","icon_name":"特","id":145744735,"image_path":"d3353e0ce844c9fc8015070c498e43bbjpeg","is_new":false,"month_sales":22,"name":"营养瑶柱炒饭套餐","original_price":64,"packing_fee":2,"price":38,"restaurant_id":320366,"restaurant_name":"避风塘（北京崇文门新世界店）","satisfy_count":4,"satisfy_rate":100,"sku_id":"14403329762","stock":9980}]}]